niceplotly_resampler/__init__.py
niceplotly_resampler/event_handlers.py
niceplotly_resampler/figure_resampler.py
niceplotly_resampler-0.1.2.dist-info/LICENSE
niceplotly_resampler-0.1.2.dist-info/METADATA
niceplotly_resampler-0.1.2.dist-info/WHEEL
niceplotly_resampler-0.1.2.dist-info/top_level.txt
niceplotly_resampler-0.1.2.dist-info/RECORD
