Metadata-Version: 2.1
Name: niceplotly-resampler
Version: 0.1.2
Summary: Visualize large time series data with plotly.py in NiceGUI
Author: Vidpic
License: MIT License
Project-URL: Repository, https://github.com/Vidpic/niceplotly-resampler
Project-URL: Issues, https://github.com/Vidpic/niceplotly-resampler/issues
Classifier: Programming Language :: Python :: 3
Classifier: Programming Language :: Python :: 3.9
Classifier: License :: OSI Approved :: MIT License
Requires-Python: >=3.9
License-File: LICENSE
Requires-Dist: numpy
Requires-Dist: plotly
Requires-Dist: nicegui
Requires-Dist: tsdownsample
